[
  {
    "key": 1,
    "title": "High flying drone",
    "date": "July 12, 2021",
    "language": "Python",
    "imageUrl": "https://cdn.mos.cms.futurecdn.net/CcBk3wsbLZzBLFunpr2pSW.jpg",
    "details": ["Made a drone", "Shot it into space", "Took pictures"]
  },
  {
    "key": 2,
    "title": "Trip to India",
    "date": "June 12, 2021",
    "language": "Python",
    "imageUrl": "https://upload.wikimedia.org/wikipedia/en/4/41/Flag_of_India.svg",
    "details": ["Made a drone", "Shot it into space", "Took pictures"]
  },
  {
    "key": 3,
    "title": "My website",
    "date": "June 11, 2019",
    "language": "ReactJS",
    "imageUrl": "https://cdn.freebiesupply.com/logos/large/2x/react-1-logo-png-transparent.png",
    "details": ["Made a drone", "Shot it into space", "Took pictures"]
  }
]
